moka_python_sdk/__init__.py
moka_python_sdk/_api_requestor.py
moka_python_sdk/_config.py
moka_python_sdk/_moka_param_injector.py
moka_python_sdk/models/_base_query.py
moka_python_sdk/models/_to_model.py
moka_python_sdk/models/library/__init__.py
moka_python_sdk/models/library/category.py
moka_python_sdk/models/library/discount.py
moka_python_sdk/models/library/entity/category.py
moka_python_sdk/models/library/entity/discount.py
moka_python_sdk/models/library/entity/gratuities.py
moka_python_sdk/models/library/entity/item.py
moka_python_sdk/models/library/entity/library.py
moka_python_sdk/models/library/entity/modifier.py
moka_python_sdk/models/library/entity/promo.py
moka_python_sdk/models/library/entity/tax.py
moka_python_sdk/models/library/gratuities.py
moka_python_sdk/models/library/item.py
moka_python_sdk/models/library/modifier.py
moka_python_sdk/models/library/promo.py
moka_python_sdk/models/library/tax.py
moka_python_sdk/models/merchant/entity/merchant.py
moka_python_sdk/models/merchant/merchant.py
moka_python_sdk/models/oauth/__init__.py
moka_python_sdk/models/oauth/entity/oauth.py
moka_python_sdk/models/oauth/oauth.py
moka_python_sdk/models/oauth/subscription/__init__.py
moka_python_sdk/models/oauth/subscription/entity/subscription.py
moka_python_sdk/models/oauth/subscription/subscription.py
moka_python_sdk/models/report/entity/report.py
moka_python_sdk/models/report/report.py
moka_python_sdk/models/transaction/__init__.py
moka_python_sdk/models/transaction/bill/bill.py
moka_python_sdk/models/transaction/bill/entity/bill.py
moka_python_sdk/models/transaction/entity/checkout.py
moka_python_sdk/models/transaction/entity/item.py
moka_python_sdk/models/transaction/entity/payment.py
moka_python_sdk/models/transaction/entity/transaction.py
moka_python_sdk/models/transaction/invoice/__init__.py
moka_python_sdk/models/transaction/invoice/entity/invoice.py
moka_python_sdk/models/transaction/invoice/invoice.py
moka_python_sdk/models/transaction/order/__init__.py
moka_python_sdk-0.1.2.dist-info/LICENSE.md
moka_python_sdk-0.1.2.dist-info/WHEEL
moka_python_sdk-0.1.2.dist-info/METADATA
moka_python_sdk-0.1.2.dist-info/RECORD
