Metadata-Version: 2.1
Name: moka-python-sdk
Version: 0.1.2
Summary: Python SDK for MOKA API
Home-page: https://github.com/landx-id/moka-python-sdk
License: MIT
Keywords: moka,api,LandX
Author: LandX Engineering
Author-email: tech@landx.id
Requires-Python: >=3.7,<4.0
Classifier: License :: OSI Approved :: MIT License
Classifier: Programming Language :: Python :: 3
Classifier: Programming Language :: Python :: 3.10
Classifier: Programming Language :: Python :: 3.7
Classifier: Programming Language :: Python :: 3.8
Classifier: Programming Language :: Python :: 3.9
Requires-Dist: dacite (>=1.6.0,<2.0.0)
Requires-Dist: pyhumps (>=3.7.2,<4.0.0)
Requires-Dist: requests (>=2.28.1,<3.0.0)
Project-URL: Repository, https://github.com/landx-id/moka-python-sdk
